CHANGELOG.rst
README.rst
pdfje/__init__.py
pdfje/atoms.py
pdfje/common.py
pdfje/compat.py
pdfje/document.py
pdfje/draw.py
pdfje/fonts/__init__.py
pdfje/fonts/builtins.py
pdfje/fonts/common.py
pdfje/fonts/embed.py
pdfje/layout/__init__.py
pdfje/layout/common.py
pdfje/layout/pages.py
pdfje/layout/paragraph.py
pdfje/layout/rule.py
pdfje/page.py
pdfje/py.typed
pdfje/resources.py
pdfje/style.py
pdfje/typeset/__init__.py
pdfje/typeset/firstfit.py
pdfje/typeset/hyphens.py
pdfje/typeset/knuth_plass.py
pdfje/typeset/layout.py
pdfje/typeset/optimum.py
pdfje/typeset/parse.py
pdfje/typeset/state.py
pdfje/typeset/words.py
pdfje/units.py
pdfje/vendor/__init__.py
pdfje/vendor/get_kerning_pairs.py
pdfje/vendor/hyphenate.py
pdfje-0.6.1.dist-info/LICENSE
pdfje-0.6.1.dist-info/METADATA
pdfje-0.6.1.dist-info/WHEEL
pdfje-0.6.1.dist-info/RECORD
