Metadata-Version: 2.1
Name: pdfje
Version: 0.6.1
Summary: Write beautiful PDFs in declarative Python
Home-page: https://github.com/ariebovenberg/pdfje
License: MIT
Keywords: pdf
Author: Arie Bovenberg
Author-email: a.c.bovenberg@gmail.com
Requires-Python: >=3.8.1,<4.0
Classifier: License :: OSI Approved :: MIT License
Classifier: Programming Language :: Python :: 3
Classifier: Programming Language :: Python :: 3.9
Classifier: Programming Language :: Python :: 3.10
Classifier: Programming Language :: Python :: 3.11
Classifier: Programming Language :: Python :: 3.12
Classifier: Programming Language :: Python :: 3.8
Provides-Extra: fonts
Provides-Extra: hyphens
Requires-Dist: fonttools (>=4.38.0,<5.0.0) ; extra == "fonts"
Requires-Dist: pyphen (>=0.13.0) ; extra == "hyphens"
Project-URL: Documentation, https://pdfje.readthedocs.io
Project-URL: Repository, https://github.com/ariebovenberg/pdfje
